appiumrunner/__init__.py
appiumrunner/__main__.py
appiumrunner/cli.py
appiumrunner/data_center.py
appiumrunner/excel_reader.py
appiumrunner/executor.py
appiumrunner/pytest_config.py
appiumrunner/step_model.py
appiumrunner/test_runner.py
AppiumRunner-0.0.1.dist-info/LICENSE
AppiumRunner-0.0.1.dist-info/METADATA
AppiumRunner-0.0.1.dist-info/WHEEL
AppiumRunner-0.0.1.dist-info/entry_points.txt
AppiumRunner-0.0.1.dist-info/top_level.txt
AppiumRunner-0.0.1.dist-info/RECORD
